Package/__init__.py
discordhelp/__init__.py
discordhelp-1.0.5.dist-info/LICENSE
discordhelp-1.0.5.dist-info/METADATA
discordhelp-1.0.5.dist-info/WHEEL
discordhelp-1.0.5.dist-info/top_level.txt
discordhelp-1.0.5.dist-info/RECORD
