Metadata-Version: 2.1
Name: discordhelp
Version: 1.0.5
Summary: A library to help with discord.py
Home-page: https://github.com/Ashvin-Ranjan/Discord-Helper
Author: Ashvin Ranjan
Author-email: me@ash.vin
License: UNKNOWN
Platform: UNKNOWN
Classifier: Programming Language :: Python :: 3
Classifier: License :: OSI Approved :: MIT License
Classifier: Operating System :: OS Independent
Requires-Python: >=3.6
Requires-Dist: discord.py
